cythonunique/README.MD
cythonunique/__init__.py
cythonunique/requirements.txt
cythonunique/thirdparty.json
cythonunique-0.11.dist-info/LICENSE.rst
cythonunique-0.11.dist-info/METADATA
cythonunique-0.11.dist-info/WHEEL
cythonunique-0.11.dist-info/top_level.txt
cythonunique-0.11.dist-info/RECORD
