Metadata-Version: 2.1
Name: cythonunique
Version: 0.11
Summary: Fast implementation of unique elements in an array - up to 30x faster than NumPy
Home-page: https://github.com/hansalemaos/cythonunique
Author: Johannes Fischer
Author-email: aulasparticularesdealemaosp@gmail.com
License: MIT
Keywords: unique,find
Classifier: Development Status :: 4 - Beta
Classifier: Programming Language :: Python :: 3 :: Only
Classifier: Programming Language :: Python :: 3.10
Classifier: Topic :: Software Development :: Libraries :: Python Modules
Classifier: Topic :: Utilities
License-File: LICENSE.rst
Requires-Dist: Cython
Requires-Dist: numpy
